LICENSE
MANIFEST.in
README.md
setup.py
QUIfixed.egg-info/PKG-INFO
QUIfixed.egg-info/SOURCES.txt
QUIfixed.egg-info/dependency_links.txt
QUIfixed.egg-info/requires.txt
QUIfixed.egg-info/top_level.txt
qgui/__init__.py
qgui/__main__.py
qgui/banner_tools.py
qgui/base_frame.py
qgui/base_tools.py
qgui/factory.py
qgui/manager.py
qgui/notebook_tools.py
qgui/os_tools.py
qgui/resources/demo/panda.jpg
qgui/resources/icon/double_down.png
qgui/resources/icon/double_up.png
qgui/resources/icon/github.png
qgui/resources/icon/play_w.png
qgui/resources/icon/up_cloud.png
qgui/theme/ttkbootstrap_themes.json
qgui/third_party/__init__.py
qgui/third_party/collapsing_frame.py