Metadata-Version: 2.1
Name: QUIfixed
Version: 0.5
Summary: /
Home-page: https://github.com/QPT-Family/QGUI
Author: fred
Author-email: 3365424882@qq.com
License: MIT
Platform: UNKNOWN
Requires-Python: >3.5
License-File: LICENSE
